plethysmo/__init__.py
plethysmo/__pkginfo__.py
plethysmo/dialogs/__init__.py
plethysmo/dialogs/parameters_dialog.py
plethysmo/dialogs/plot_dialog.py
plethysmo/dialogs/roi_dialog.py
plethysmo/dialogs/statistics_dialog.py
plethysmo/icons/plethysmo.ico
plethysmo/icons/plethysmo.png
plethysmo/kernel/__init__.py
plethysmo/kernel/edf_file_reader.py
plethysmo/kernel/parameters.py
plethysmo/kernel/roi.py
plethysmo/models/__init__.py
plethysmo/models/edf_files_list_model.py
plethysmo/models/excluded_zones_list_model.py
plethysmo/models/intervals_list_model.py
plethysmo/models/pandas_data_model.py
plethysmo/models/rois_list_model.py
plethysmo/utils/progress_bar.py
plethysmo/utils/signal.py
plethysmo/views/__init__.py
plethysmo/views/copy_pastable_tableview.py
plethysmo/views/deselectable_listview.py
plethysmo/views/main_window.py
plethysmo/widgets/logger_widget.py
plethysmo/widgets/plot_widget.py
plethysmo-0.0.0.data/scripts/plethysmo
plethysmo-0.0.0.dist-info/LICENSE
plethysmo-0.0.0.dist-info/METADATA
plethysmo-0.0.0.dist-info/WHEEL
plethysmo-0.0.0.dist-info/top_level.txt
plethysmo-0.0.0.dist-info/RECORD
